Py3PDF/__init__.py
Py3PDF/_version.py
Py3PDF/filters.py
Py3PDF/generic.py
Py3PDF/merger.py
Py3PDF/pagerange.py
Py3PDF/pdf.py
Py3PDF/utils.py
Py3PDF/xmp.py
Py3PDF-1.26.1.dist-info/LICENSE
Py3PDF-1.26.1.dist-info/METADATA
Py3PDF-1.26.1.dist-info/WHEEL
Py3PDF-1.26.1.dist-info/top_level.txt
Py3PDF-1.26.1.dist-info/RECORD
