Metadata-Version: 2.1
Name: Py3PDF
Version: 1.26.1
Summary: PyPDF2 fork
Home-page: https://github.com/LateNightLearning/Py3PDF
Author: Jacod Shax
Author-email: igotlocekdout2day@gmail.com
License: UNKNOWN
Platform: UNKNOWN
Classifier: Development Status :: 5 - Production/Stable
Classifier: Intended Audience :: Developers
Classifier: License :: OSI Approved :: BSD License
Classifier: Programming Language :: Python :: 2
Classifier: Programming Language :: Python :: 3
Classifier: Operating System :: OS Independent
Classifier: Topic :: Software Development :: Libraries :: Python Modules
License-File: LICENSE
